Metadata-Version: 2.1
Name: odoo12-addon-portal-partner-select-all
Version: 12.0.1.0.2
Summary: Portal Partner Select All
Home-page: https://www.github.com/OCA/partner-contact
Author: Tecnativa,Odoo Community Association (OCA)
Author-email: support@odoo-community.org
License: AGPL-3
Platform: UNKNOWN
Classifier: Programming Language :: Python
Classifier: Framework :: Odoo
Classifier: License :: OSI Approved :: GNU Affero General Public License v3
Requires-Python: >=3.5
Requires-Dist: odoo (<12.1dev,>=12.0a)
